jazyk/__init__.py
jazyk/langs.py
jazyk/main.py
jazyk-0.4.0.dist-info/METADATA
jazyk-0.4.0.dist-info/WHEEL
jazyk-0.4.0.dist-info/entry_points.txt
jazyk-0.4.0.dist-info/RECORD
