Metadata-Version: 2.3
Name: jazyk
Version: 0.4.0
Summary: 
Author: walid
Author-email: walid.sa3d@gmail.com
Requires-Python: >=3.10,<4.0
Classifier: Programming Language :: Python :: 3
Classifier: Programming Language :: Python :: 3.10
Classifier: Programming Language :: Python :: 3.11
Classifier: Programming Language :: Python :: 3.12
Classifier: Programming Language :: Python :: 3.13
Requires-Dist: click (>=8.1.7,<9.0.0)
Requires-Dist: deep-translator (>=1.11.4,<2.0.0)
Requires-Dist: pyfiglet (>=1.0.2,<2.0.0)
Requires-Dist: rich (>=13.7.1,<14.0.0)
Requires-Dist: uroman (>=1.3.1.1,<2.0.0.0)
